spi_peripheral_basic/top_spi.v
module spi_hardip_top
#(
    parameter BYTE_W = 8
)
(
    //input wire m_clk,
    input wire mosi_pad,
    input wire sck_pad,
    input wire csn_pad,
    output wire miso_pad,
    
    output reg DRDY,
  //  input wire DWRITTEN,

    output reg [(BYTE_W - 1):0]d_recieved,
    input wire [(BYTE_W - 1):0]d_to_send
);

    reg [(BYTE_W-1):0]spi_rx;
    
    reg [(BYTE_W):0]spi_tx;
    
    reg [2:0]clk_ctr;

    //assign miso_pad = (csn_pad) ? 1'b0 : spi_tx[0];
    assign miso_pad = spi_tx[7];

    initial begin
        d_recieved = 0;
        // RP2040 forcing MSB first
        spi_rx = 0;
        
        //spi_tx = d_to_send;
        // Problem child here...
        spi_tx = 0;

        DRDY = 0;

        clk_ctr = 0;
    end

    // Hardcoded mode 0
    always @ (posedge sck_pad) begin
        if(!csn_pad) begin
            spi_rx = spi_rx << 1;
            spi_rx[0] = mosi_pad;
            //spi_rx <= {mosi_pad, spi_rx >> 1};
            clk_ctr = clk_ctr + 1;
            if(clk_ctr == 3'b000) begin
                d_recieved = spi_rx;
                DRDY = 1'b1;
            end
            else DRDY <= 1'b0;
        end
    end

    always @ (negedge sck_pad) begin
        //if(!csn_pad && clk_ctr) begin
        if(!csn_pad) begin
            spi_tx = spi_tx << 1;
        end
        
        if(!clk_ctr) spi_tx <= {1'b0,d_to_send[(BYTE_W - 1):0]};
    end

/*
    always @ (posedge DWRITTEN) begin
        DRDY <= 1'b0;
    end
*/
endmodule

spi_peripheral_basic/spi_module_tb.v
`timescale 1ns/1ps

module spi_module_tb();

/*
module spi_hardip_top
#(
    parameter BYTE_W = 8
)
(
    //input wire m_clk,
    input wire mosi_pad,
    input wire sck_pad,
    input wire csn_pad,
    output wire miso_pad,
    
    output reg DRDY,
    input wire DWRITTEN,

    output reg [(BYTE_W - 1):0]d_recieved,
    input wire [(BYTE_W - 1):0]d_to_send
);
*/

    reg sck, mosi, cs;
    wire miso, dready;

    reg [7:0]dts;
    wire [7:0]drx;

    spi_hardip_top spi_dut
    (
        .mosi_pad(mosi),
        .miso_pad(miso),
        .csn_pad(cs),
        .sck_pad(sck),
        .DRDY(dready),

        .d_recieved(drx),
        .d_to_send(drx)
    );

    initial begin
        mosi = 0;
        cs = 1;
    
        dts = 0;

        #45;
        cs = 0;
        mosi = 1;
/*
        #20;
        mosi = 0;
        #20;
        mosi = 1;
        #20;
        mosi = 0;
        #20;
        mosi = 0;
        #20;
        mosi = 1;
        #20;
        mosi = 0;
        #20;
        mosi = 0;
        #20;
        mosi = 1;
        #20;
        mosi = 0;
        #20;
        mosi = 0;
        #20;
        mosi = 1;
        #20;
        mosi = 0;
        #20;
        mosi = 0;
        #20;
        mosi = 1;
        #20;
        mosi = 0;
*/
        #2000;
        

        $finish;
    end

    initial
   
    begin
        $dumpfile("spi_module_tb.vcd");
        $dumpvars(0,spi_module_tb);
    end

    initial begin
        sck = 0;
        forever begin
            #10;
            sck = ~sck;
        end
    end
endmodule

spi_peripheral_basic/spi_module_tb.vcd
$date
	Wed Mar 22 15:09:30 2023
$end
$version
	Icarus Verilog
$end
$timescale
	1ps
$end
$scope module spi_module_tb $end
$var wire 1 ! miso $end
$var wire 8 " drx [7:0] $end
$var wire 1 # dready $end
$var reg 1 $ cs $end
$var reg 8 % dts [7:0] $end
$var reg 1 & mosi $end
$var reg 1 ' sck $end
$scope module spi_dut $end
$var wire 1 $ csn_pad $end
$var wire 8 ( d_to_send [7:0] $end
$var wire 1 & mosi_pad $end
$var wire 1 ' sck_pad $end
$var wire 1 ! miso_pad $end
$var reg 1 # DRDY $end
$var reg 3 ) clk_ctr [2:0] $end
$var reg 8 * d_recieved [7:0] $end
$var reg 8 + spi_rx [7:0] $end
$var reg 8 , spi_tx [7:0] $end
$upscope $end
$upscope $end
$enddefinitions $end
#0
$dumpvars
b0 ,
b0 +
b0 *
b0 )
b0 (
0'
0&
b0 %
1$
0#
b0 "
0!
$end
#10000
1'
#20000
0'
#30000
1'
#40000
0'
#45000
1&
0$
#50000
b1 )
b1 +
1'
#60000
0'
#70000
b10 )
b11 +
1'
#80000
0'
#90000
b11 )
b111 +
1'
#100000
0'
#110000
b100 )
b1111 +
1'
#120000
0'
#130000
b101 )
b11111 +
1'
#140000
0'
#150000
b110 )
b111111 +
1'
#160000
0'
#170000
b111 )
b1111111 +
1'
#180000
0'
#190000
1!
b11111111 ,
1#
b11111111 "
b11111111 (
b11111111 *
b0 )
b11111111 +
1'
#200000
b11111110 ,
0'
#210000
0#
b1 )
b11111111 +
1'
#220000
b11111100 ,
0'
#230000
b10 )
b11111111 +
1'
#240000
b11111000 ,
0'
#250000
b11 )
b11111111 +
1'
#260000
b11110000 ,
0'
#270000
b100 )
b11111111 +
1'
#280000
b11100000 ,
0'
#290000
b101 )
b11111111 +
1'
#300000
b11000000 ,
0'
#310000
b110 )
b11111111 +
1'
#320000
b10000000 ,
0'
#330000
b111 )
b11111111 +
1'
#340000
0!
b0 ,
0'
#350000
1!
b11111111 ,
1#
b0 )
b11111111 +
1'
#360000
b11111110 ,
0'
#370000
0#
b1 )
b11111111 +
1'
#380000
b11111100 ,
0'
#390000
b10 )
b11111111 +
1'
#400000
b11111000 ,
0'
#410000
b11 )
b11111111 +
1'
#420000
b11110000 ,
0'
#430000
b100 )
b11111111 +
1'
#440000
b11100000 ,
0'
#450000
b101 )
b11111111 +
1'
#460000
b11000000 ,
0'
#470000
b110 )
b11111111 +
1'
#480000
b10000000 ,
0'
#490000
b111 )
b11111111 +
1'
#500000
0!
b0 ,
0'
#510000
1!
b11111111 ,
1#
b0 )
b11111111 +
1'
#520000
b11111110 ,
0'
#530000
0#
b1 )
b11111111 +
1'
#540000
b11111100 ,
0'
#550000
b10 )
b11111111 +
1'
#560000
b11111000 ,
0'
#570000
b11 )
b11111111 +
1'
#580000
b11110000 ,
0'
#590000
b100 )
b11111111 +
1'
#600000
b11100000 ,
0'
#610000
b101 )
b11111111 +
1'
#620000
b11000000 ,
0'
#630000
b110 )
b11111111 +
1'
#640000
b10000000 ,
0'
#650000
b111 )
b11111111 +
1'
#660000
0!
b0 ,
0'
#670000
1!
b11111111 ,
1#
b0 )
b11111111 +
1'
#680000
b11111110 ,
0'
#690000
0#
b1 )
b11111111 +
1'
#700000
b11111100 ,
0'
#710000
b10 )
b11111111 +
1'
#720000
b11111000 ,
0'
#730000
b11 )
b11111111 +
1'
#740000
b11110000 ,
0'
#750000
b100 )
b11111111 +
1'
#760000
b11100000 ,
0'
#770000
b101 )
b11111111 +
1'
#780000
b11000000 ,
0'
#790000
b110 )
b11111111 +
1'
#800000
b10000000 ,
0'
#810000
b111 )
b11111111 +
1'
#820000
0!
b0 ,
0'
#830000
1!
b11111111 ,
1#
b0 )
b11111111 +
1'
#840000
b11111110 ,
0'
#850000
0#
b1 )
b11111111 +
1'
#860000
b11111100 ,
0'
#870000
b10 )
b11111111 +
1'
#880000
b11111000 ,
0'
#890000
b11 )
b11111111 +
1'
#900000
b11110000 ,
0'
#910000
b100 )
b11111111 +
1'
#920000
b11100000 ,
0'
#930000
b101 )
b11111111 +
1'
#940000
b11000000 ,
0'
#950000
b110 )
b11111111 +
1'
#960000
b10000000 ,
0'
#970000
b111 )
b11111111 +
1'
#980000
0!
b0 ,
0'
#990000
1!
b11111111 ,
1#
b0 )
b11111111 +
1'
#1000000
b11111110 ,
0'
#1010000
0#
b1 )
b11111111 +
1'
#1020000
b11111100 ,
0'
#1030000
b10 )
b11111111 +
1'
#1040000
b11111000 ,
0'
#1050000
b11 )
b11111111 +
1'
#1060000
b11110000 ,
0'
#1070000
b100 )
b11111111 +
1'
#1080000
b11100000 ,
0'
#1090000
b101 )
b11111111 +
1'
#1100000
b11000000 ,
0'
#1110000
b110 )
b11111111 +
1'
#1120000
b10000000 ,
0'
#1130000
b111 )
b11111111 +
1'
#1140000
0!
b0 ,
0'
#1150000
1!
b11111111 ,
1#
b0 )
b11111111 +
1'
#1160000
b11111110 ,
0'
#1170000
0#
b1 )
b11111111 +
1'
#1180000
b11111100 ,
0'
#1190000
b10 )
b11111111 +
1'
#1200000
b11111000 ,
0'
#1210000
b11 )
b11111111 +
1'
#1220000
b11110000 ,
0'
#1230000
b100 )
b11111111 +
1'
#1240000
b11100000 ,
0'
#1250000
b101 )
b11111111 +
1'
#1260000
b11000000 ,
0'
#1270000
b110 )
b11111111 +
1'
#1280000
b10000000 ,
0'
#1290000
b111 )
b11111111 +
1'
#1300000
0!
b0 ,
0'
#1310000
1!
b11111111 ,
1#
b0 )
b11111111 +
1'
#1320000
b11111110 ,
0'
#1330000
0#
b1 )
b11111111 +
1'
#1340000
b11111100 ,
0'
#1350000
b10 )
b11111111 +
1'
#1360000
b11111000 ,
0'
#1370000
b11 )
b11111111 +
1'
#1380000
b11110000 ,
0'
#1390000
b100 )
b11111111 +
1'
#1400000
b11100000 ,
0'
#1410000
b101 )
b11111111 +
1'
#1420000
b11000000 ,
0'
#1430000
b110 )
b11111111 +
1'
#1440000
b10000000 ,
0'
#1450000
b111 )
b11111111 +
1'
#1460000
0!
b0 ,
0'
#1470000
1!
b11111111 ,
1#
b0 )
b11111111 +
1'
#1480000
b11111110 ,
0'
#1490000
0#
b1 )
b11111111 +
1'
#1500000
b11111100 ,
0'
#1510000
b10 )
b11111111 +
1'
#1520000
b11111000 ,
0'
#1530000
b11 )
b11111111 +
1'
#1540000
b11110000 ,
0'
#1550000
b100 )
b11111111 +
1'
#1560000
b11100000 ,
0'
#1570000
b101 )
b11111111 +
1'
#1580000
b11000000 ,
0'
#1590000
b110 )
b11111111 +
1'
#1600000
b10000000 ,
0'
#1610000
b111 )
b11111111 +
1'
#1620000
0!
b0 ,
0'
#1630000
1!
b11111111 ,
1#
b0 )
b11111111 +
1'
#1640000
b11111110 ,
0'
#1650000
0#
b1 )
b11111111 +
1'
#1660000
b11111100 ,
0'
#1670000
b10 )
b11111111 +
1'
#1680000
b11111000 ,
0'
#1690000
b11 )
b11111111 +
1'
#1700000
b11110000 ,
0'
#1710000
b100 )
b11111111 +
1'
#1720000
b11100000 ,
0'
#1730000
b101 )
b11111111 +
1'
#1740000
b11000000 ,
0'
#1750000
b110 )
b11111111 +
1'
#1760000
b10000000 ,
0'
#1770000
b111 )
b11111111 +
1'
#1780000
0!
b0 ,
0'
#1790000
1!
b11111111 ,
1#
b0 )
b11111111 +
1'
#1800000
b11111110 ,
0'
#1810000
0#
b1 )
b11111111 +
1'
#1820000
b11111100 ,
0'
#1830000
b10 )
b11111111 +
1'
#1840000
b11111000 ,
0'
#1850000
b11 )
b11111111 +
1'
#1860000
b11110000 ,
0'
#1870000
b100 )
b11111111 +
1'
#1880000
b11100000 ,
0'
#1890000
b101 )
b11111111 +
1'
#1900000
b11000000 ,
0'
#1910000
b110 )
b11111111 +
1'
#1920000
b10000000 ,
0'
#1930000
b111 )
b11111111 +
1'
#1940000
0!
b0 ,
0'
#1950000
1!
b11111111 ,
1#
b0 )
b11111111 +
1'
#1960000
b11111110 ,
0'
#1970000
0#
b1 )
b11111111 +
1'
#1980000
b11111100 ,
0'
#1990000
b10 )
b11111111 +
1'
#2000000
b11111000 ,
0'
#2010000
b11 )
b11111111 +
1'
#2020000
b11110000 ,
0'
#2030000
b100 )
b11111111 +
1'
#2040000
b11100000 ,
0'
